LICENSE
MANIFEST.in
README.rst
setup.cfg
setup.py
examples/__init__.py
examples/index.html
examples/show.py
examples/data/custom_grammar.md
examples/data/hello_world.md
examples/data/markdown_help.md
examples/data/style.css
mpiece/__init__.py
mpiece/core.py
mpiece/lexer.py
mpiece/renderer.py
mpiece.egg-info/PKG-INFO
mpiece.egg-info/SOURCES.txt
mpiece.egg-info/dependency_links.txt
mpiece.egg-info/not-zip-safe
mpiece.egg-info/top_level.txt
tests/__init__.py
tests/test.py
tests/data/test_blockquote.html
tests/data/test_blockquote.md
tests/data/test_code.html
tests/data/test_code.md
tests/data/test_escape.html
tests/data/test_escape.md
tests/data/test_escape_metachars.html
tests/data/test_escape_metachars.md
tests/data/test_exclude.html
tests/data/test_exclude.md
tests/data/test_footnotes.html
tests/data/test_footnotes.md
tests/data/test_header.html
tests/data/test_header.md
tests/data/test_links_and_images.html
tests/data/test_links_and_images.md
tests/data/test_list.html
tests/data/test_list.md
tests/data/test_no_escape.html
tests/data/test_no_escape.md
tests/data/test_styles.html
tests/data/test_styles.md
tests/data/test_table.html
tests/data/test_table.md
tests/data/test_utf_characters.html
tests/data/test_utf_characters.md